[
    {
        "service": "Finances Management",
        "description": "For today's Forex traders, this means that they need no longer feel Forex-deprived access."
    },

    {
        "service": "Crypto Dashboard",
        "description": "For today's Forex traders, this means that they need no longer feel Forex-deprived access."
    },

    {
        "service": "Privacy and Policy",
        "description": "For today's Forex traders, this means that they need no longer feel Forex-deprived access."
    },

    {
        "service": "Increased Stats",
        "description": "For today's Forex traders, this means that they need no longer feel Forex-deprived access."
    },

    {
        "service": "Multiple Facets",
        "description": "For today's Forex traders, this means that they need no longer feel Forex-deprived access."
    },

    {
        "service": "Money Bonuses",
        "description": "For today's Forex traders, this means that they need no longer feel Forex-deprived access."
    }
]
